{
    "applicationNumber": "BR 10 2012 010651-5",
    "filingDate": "04/05/2012",
    "grantDate": "31/07/2018",
    "title": "EMULS\u00d5ES DE \u00d3LEO EM \u00c1GUA DE ALTA RESIST\u00caNCIA, EST\u00c1VEIS",
    "priorityClaims": [
        {
            "countryCode": "US",
            "priorityNumber": "61/482,716",
            "priorityDate": "05/05/2011"
        }
    ],
    "events": [
        {
            "code": "9.1",
            "description": "Deferimento",
            "bulletinNumber ": "2474"
        },
        {
            "code": "16.1",
            "description": "Concess\u00e3o de Patente ou Certificado de Adi\u00e7\u00e3o de Inven\u00e7\u00e3o",
            "bulletinNumber ": "2482"
        },
        {
            "code": "25.4",
            "description": "Altera\u00e7\u00e3o de Nome Deferida",
            "bulletinNumber ": "2701"
        }
    ],
    "inventors": [
        "HONG ZHANG",
        "HOLGER TANK",
        "FRANKLIN N KEENEY",
        "MEI LI",
        "MARCO A TAVARES DO NASCIMENTO"
    ],
    "holders": [
        60
    ],
    "ipcCodes": [
        "A01P 13/00",
        "A01N 57/20",
        "A01N 25/04"
    ]
}