{
    "applicationNumber": "BR 10 2016 024530-3",
    "filingDate": "20/10/2016",
    "grantDate": "24/08/2021",
    "title": "BEBIDA L\u00c1CTEA DE BAIXO TEOR DE LACTOSE ADICIONADA COM PRODUTOS DA ULTRAFILTRA\u00c7\u00c3O DO SORO DE LEITE E SEU PROCESSO DE OBTEN\u00c7\u00c3O",
    "events": [
        {
            "code": "6.1",
            "description": "Exig\u00eancia T\u00e9cnica",
            "bulletinNumber ": "2622"
        },
        {
            "code": "9.1",
            "description": "Deferimento",
            "bulletinNumber ": "2638"
        },
        {
            "code": "16.1",
            "description": "Concess\u00e3o de Patente ou Certificado de Adi\u00e7\u00e3o de Inven\u00e7\u00e3o",
            "bulletinNumber ": "2642"
        },
        {
            "code": "21.6",
            "description": "Extin\u00e7\u00e3o da patente para fins da restaura\u00e7\u00e3o nos termos do art. 87 da LPI.",
            "bulletinNumber ": "2745"
        },
        {
            "code": "24.10",
            "description": "Manuten\u00e7\u00e3o da Extin\u00e7\u00e3o - Art. 78 inciso IV da LPI",
            "bulletinNumber ": "2761"
        }
    ],
    "inventors": [
        "VANDR\u00c9 BARBOSA BRI\u00c3O",
        "BRUNA SEGUENKA",
        "VERA MARIA RODRIGUES",
        "CRECIANA MARIA ENDRES"
    ],
    "holders": [
        990
    ],
    "ipcCodes": [
        "A23J 1/20",
        "A23C 21/02",
        "A23C 9/12"
    ]
}