{
    "applicationNumber": "BR 11 2018 072370-3",
    "filingDate": "02/05/2017",
    "grantDate": null,
    "title": "GERADOR S\u00cdNCRONO DE UMA INSTALA\u00c7\u00c3O DE ENERGIA E\u00d3LICA SEM ENGRENAGEM, M\u00c9TODO PARA PRODUZIR UM GERADOR S\u00cdNCRONO, E, USO DE BOBINAS DE ALUM\u00cdNIO PR\u00c9-FORMADAS E BOBINAS DE COBRE PR\u00c9-FORMADAS",
    "nationalPhaseDate": [
        "30/10/2018"
    ],
    "internationalApplication": {
        "pctNumber": "PCT EP2017/060352",
        "pctDate": "02/05/2017",
        "wipoNumber": null,
        "wipoDate": null
    },
    "priorityClaims": [
        {
            "countryCode": "DE",
            "priorityNumber": "10 2016 108 712.2",
            "priorityDate": "11/05/2016"
        }
    ],
    "events": [
        {
            "code": "1.1",
            "description": "Publica\u00e7\u00e3o Internacional \u2013 PCT. Apresenta\u00e7\u00e3o de peti\u00e7\u00e3o de requerimento de entrada na fase nacional",
            "bulletinNumber ": "2497"
        },
        {
            "code": "1.3",
            "description": "Notifica\u00e7\u00e3o - Fase Nacional - PCT",
            "bulletinNumber ": "2511"
        },
        {
            "code": "11.1",
            "description": "Arquivamento - Art. 33 da LPI",
            "bulletinNumber ": "2588"
        },
        {
            "code": "11.1.1",
            "description": "Arquivamento definitivo - Art. 33 da LPI",
            "bulletinNumber ": "2601"
        },
        {
            "code": "15.35",
            "description": "Atualiza\u00e7\u00e3o de informa\u00e7\u00f5es no portal",
            "bulletinNumber ": "2644"
        }
    ],
    "inventors": [
        "JAN CARSTEN ZIEMS",
        "JOCHEN R\u00d6ER"
    ],
    "holders": [
        96024
    ],
    "ipcCodes": [
        "H02K 15/00",
        "H02K 1/16",
        "H02K 3/02"
    ]
}