{
    "applicationNumber": "BR 11 2020 016997-8",
    "filingDate": "12/04/2019",
    "grantDate": null,
    "title": "MOL\u00c9CULAS DE LIGA\u00c7\u00c3O E DE \u00c1CIDO NUCLEICO ISOLADA, VETOR, C\u00c9LULA HOSPEDEIRA, M\u00c9TODOS PARA PRODUZIR A MOL\u00c9CULA DE LIGA\u00c7\u00c3O, PARA TRATAR UM INDIV\u00cdDUO COM C\u00c2NCER E PARA REGULAR POSITIVAMENTE OU PROLONGAR A ATIVIDADE DE C\u00c9LULAS T, COMPOSI\u00c7\u00c3O FARMAC\u00caUTICA E USO DA MOL\u00c9CULA DE LIGA\u00c7\u00c3O",
    "nationalPhaseDate": [
        "20/08/2020"
    ],
    "internationalApplication": {
        "pctNumber": "PCT EP2019/059391",
        "pctDate": "12/04/2019",
        "wipoNumber": null,
        "wipoDate": null
    },
    "priorityClaims": [
        {
            "countryCode": "EP",
            "priorityNumber": "18167147.0",
            "priorityDate": "13/04/2018"
        }
    ],
    "events": [
        {
            "code": "1.1",
            "description": "Publica\u00e7\u00e3o Internacional \u2013 PCT. Apresenta\u00e7\u00e3o de peti\u00e7\u00e3o de requerimento de entrada na fase nacional",
            "bulletinNumber ": "2598"
        },
        {
            "code": "1.3",
            "description": "Notifica\u00e7\u00e3o - Fase Nacional - PCT",
            "bulletinNumber ": "2611"
        },
        {
            "code": "15.35",
            "description": "Atualiza\u00e7\u00e3o de informa\u00e7\u00f5es no portal",
            "bulletinNumber ": "2658"
        }
    ],
    "inventors": [
        "CLAUDIA FERRARA KOLLER",
        "TEEMU TAPANI JUNTTILA",
        "CHRISTIAN KLEIN",
        "PABLO UMANA",
        "CHRISTINA CLAUS"
    ],
    "holders": [
        61582
    ],
    "ipcCodes": [
        "A61P 35/00",
        "A61K 39/395",
        "C07K 16/28",
        "C07K 14/52",
        "C07K 16/32"
    ]
}