{
    "applicationNumber": "BR 11 2021 026807-3",
    "filingDate": "01/07/2020",
    "grantDate": null,
    "title": "IMPRESS\u00c3O 3D FDM DE LENTE \u00d3PTICA COM ALTA CLAREZA E RESIST\u00caNCIA MEC\u00c2NICA",
    "nationalPhaseDate": [
        "30/12/2021"
    ],
    "internationalApplication": {
        "pctNumber": "PCT EP2020/068457",
        "pctDate": "01/07/2020",
        "wipoNumber": null,
        "wipoDate": null
    },
    "priorityClaims": [
        {
            "countryCode": "EP",
            "priorityNumber": "19315055.4",
            "priorityDate": "02/07/2019"
        }
    ],
    "events": [
        {
            "code": "1.1",
            "description": "Publica\u00e7\u00e3o Internacional \u2013 PCT. Apresenta\u00e7\u00e3o de peti\u00e7\u00e3o de requerimento de entrada na fase nacional",
            "bulletinNumber ": "2662"
        },
        {
            "code": "1.3",
            "description": "Notifica\u00e7\u00e3o - Fase Nacional - PCT",
            "bulletinNumber ": "2667"
        },
        {
            "code": "6.23",
            "description": "Exig\u00eancia preliminar - pedidos com buscas realizadas por outros Escrit\u00f3rios de Patentes - Art. 36 da LPI",
            "bulletinNumber ": "2769"
        }
    ],
    "inventors": [
        "HAIFENG SHAN",
        "WEN CHIU",
        "AREF JALLOULI"
    ],
    "holders": [
        81123
    ],
    "ipcCodes": [
        "D01F 1/10",
        "D01D 5/34",
        "B33Y 70/00",
        "B29D 11/00",
        "D01F 8/00"
    ]
}