{
    "applicationNumber": "BR 20 2021 020261-6",
    "filingDate": "08/10/2021",
    "grantDate": null,
    "title": "SISTEMA AUT\u00d4NOMO COMPACTO DE PRODU\u00c7\u00c3O E ALIMENTA\u00c7\u00c3O  DE ENERGIA EL\u00c9TRICA TIPO TOTEM PARA CARGA E RECARGA DE VE\u00cdCULOS TIPO MOTONETAS EL\u00c9TRICAS, MOTOS EL\u00c9TRICAS, SCOOTERS EL\u00c9TRICAS, PATINETES EL\u00c9TRICOS",
    "events": [
        {
            "code": "2.10",
            "description": "Requerimento de Pedido de Patente ou Certificado de Adi\u00e7\u00e3o de Inven\u00e7\u00e3o",
            "bulletinNumber ": "2650"
        },
        {
            "code": "2.1",
            "description": "Pedido de Patente ou Certificado de Adi\u00e7\u00e3o de Inven\u00e7\u00e3o depositado",
            "bulletinNumber ": "2662"
        },
        {
            "code": "3.1",
            "description": "Publica\u00e7\u00e3o do Pedido de Patente ou de Certificado de Adi\u00e7\u00e3o de Inven\u00e7\u00e3o",
            "bulletinNumber ": "2729"
        },
        {
            "code": "8.6",
            "description": "Arquivamento - Art. 86 da LPI",
            "bulletinNumber ": "2808"
        }
    ],
    "inventors": [
        "DANILO JOS\u00c9 FERREIRA"
    ],
    "holders": [
        366056,
        366054,
        366055
    ],
    "ipcCodes": [
        "G09F 1/06",
        "G09F 15/00"
    ]
}