{
    "applicationNumber": "PI 0803467-2",
    "filingDate": "09/09/2008",
    "grantDate": null,
    "title": "SISTEMA DE CONTROLE E RETORNO DE \u00c1GUA PARA TUBULA\u00c7\u00c3O DE DISTRIBUI\u00c7\u00c3O DE \u00c1GUA QUENTE EM AQUECEDOR DE PASSAGEM",
    "events": [
        {
            "code": "7.1",
            "description": "Conhecimento de Parecer T\u00e9cnico",
            "bulletinNumber ": "2504"
        },
        {
            "code": "9.2",
            "description": "Indeferimento",
            "bulletinNumber ": "2519"
        },
        {
            "code": "9.2.4",
            "description": "Manuten\u00e7\u00e3o do Indeferimento",
            "bulletinNumber ": "2531"
        }
    ],
    "inventors": [],
    "holders": [
        389537
    ],
    "ipcCodes": []
}