{
    "applicationNumber": "PI 0616306-8",
    "filingDate": "04/09/2006",
    "grantDate": null,
    "title": "DISPOSITIVO MOTRIZ PARA LAMINADOR",
    "events": [
        {
            "code": "6.6.1",
            "description": "Exig\u00eancia Formal - art. 38 (I) da Lei 13.123/2015",
            "bulletinNumber ": "2508"
        },
        {
            "code": "7.1",
            "description": "Conhecimento de Parecer T\u00e9cnico",
            "bulletinNumber ": "2525"
        },
        {
            "code": "9.1",
            "description": "Deferimento",
            "bulletinNumber ": "2583"
        },
        {
            "code": "11.4",
            "description": "Arquivamento - Art. 38 \u00a7 2\u00b0 da LPI",
            "bulletinNumber ": "2602"
        }
    ],
    "inventors": [],
    "holders": [
        376248
    ],
    "ipcCodes": []
}