{
    "applicationNumber": "PI 0903369-6",
    "filingDate": "09/09/2009",
    "grantDate": null,
    "title": "COMPOSI\u00c7\u00c3O LUBRIFICANTE E M\u00c9TODO DE LUBRIFICA\u00c7\u00c3O DE UMA TURBINA",
    "priorityClaims": [
        {
            "countryCode": "US",
            "priorityNumber": "12/288,222",
            "priorityDate": "17/10/2008"
        }
    ],
    "events": [
        {
            "code": "12.2",
            "description": "Recurso Contra o Indeferimento",
            "bulletinNumber ": "2474"
        },
        {
            "code": "100",
            "description": "Recurso conhecido e provido. Reformada a Decis\u00e3o recorrida e deferido o pedido",
            "bulletinNumber ": "2635"
        },
        {
            "code": "16.1",
            "description": "Concess\u00e3o de Patente ou Certificado de Adi\u00e7\u00e3o de Inven\u00e7\u00e3o",
            "bulletinNumber ": "2650"
        }
    ],
    "inventors": [
        "HELEN T RYAN",
        "RICKY SHYAM PRASAD",
        "JOHN M TAYLOR"
    ],
    "holders": [
        142
    ],
    "ipcCodes": [
        "C10M 101/02",
        "C10M 133/42",
        "C10M 133/12"
    ]
}