{"numero":"BR 12 2022 022633-7","dataDeposito":"05/10/2016","titulares":[{"nomeCompleto":"DSM IP ASSETS B.V.","pais":"NL"}],"divisaoPedido":{"dataDeposito":"05/10/2016","numero":"BR 11 2018 006807-1"},"despachos":[{"codigo":"2.10","titulo":"Requerimento de Pedido de Patente ou Certificado de Adição de Invenção","rpi":"2706"},{"codigo":"2.4","titulo":"Notificação de Depósito do Pedido Dividido - Art 26 inciso I da LPI","rpi":"2709"},{"codigo":"9.2","titulo":"Indeferimento","rpi":"2711"},{"codigo":"12.2","titulo":"Recurso Contra o Indeferimento","rpi":"2725"}],"titulo":"ÓLEO COMPREENDENDO UMA FRAÇÃO ÉSTER, PRODUTO ALIMENTAR, COMPOSIÇÃO COSMÉTICA OU COMPOSIÇÃO FARMACÊUTICA"}