{"numero":"BR 11 2023 022862-0","pedidoInternacional":{"numeroPCT":"PCT EP2022/062226","dataPCT":"05/05/2022"},"publicacaoInternacional":{"numeroOMPI":"WO 2022/234053","dataOMPI":"10/11/2022"},"IPC":["C12N 1/20","A61K 35/74"],"prioridadesUnionistas":[{"siglaPais":"EP","numeroPrioridade":"21172578.3","dataPrioridade":"06/05/2021"}],"despachos":[{"codigo":"1.1","titulo":"Pedido Internacional PCT Publicado. Petição de Requerimento de Entrada na Fase Nacional Recebida","rpi":"2757"},{"codigo":"1.3","titulo":"Pedido PCT Admitido na Fase Nacional","rpi":"2768"}],"dataDeposito":"05/05/2022","dataFaseNacional":"31/10/2023","titulo":"MÉTODOS AUXILIADOS POR COMPUTADOR, MÉTODO DE PRODUÇÃO DE UM PRODUTO DE COMUNIDADES COMPLEXAS DE MICRORGANISMOS, DISPOSITIVO DE COMPUTADOR E MEIO LEGÍVEL POR COMPUTADOR NÃO TRANSITÓRIO","titulares":[{"nomeCompleto":"MAAT PHARMA","pais":"FR"}],"inventores":["HERVÉ AFFAGARD","CAROLE SCHWINTNER","EMMANUEL PRESTAT"]}