{"numero":"BR 11 2015 006442-6","dataDeposito":"18/09/2013","titulares":[{"nomeCompleto":"DOW GLOBAL TECHNOLOGIES LLC","pais":"US"},{"nomeCompleto":"ROHM AND HAAS COMPANY","pais":"US"}],"despachos":[{"codigo":"6.20","titulo":"ExigênciaPré-Exame – Art. 34 da LPI","rpi":"2524"},{"codigo":"9.1","titulo":"Deferimento","rpi":"2543"},{"codigo":"16.1","titulo":"Concessão de Patente ou Certificado de Adição de Invenção","rpi":"2551"},{"codigo":"21.6","titulo":"Extinção da patente para fins da restauração nos termos do art. 87 da LPI.","rpi":"2688"},{"codigo":"24.10","titulo":"Manutenção da Extinção - Art. 78 inciso IV da LPI","rpi":"2703"}],"titulo":"COMPOSIÇÃO GEL TIPO ÓLEO PARA CUIDADO DA PELE","IPC":["A61K 8/81","A61K 8/31","A61Q 11/00","A61K 8/04"],"inventores":["Curtis Schwartz","Ying O'Connor","THOMAS P. CLARK","John W. Kramer","THOMAS H. PETERSON","Qichun Wan"],"prioridadesUnionistas":[{"siglaPais":"US","numeroPrioridade":"61/704,663","dataPrioridade":"24/09/2012"}],"dataConcessao":"26/11/2019"}