{"numero":"BR 10 2021 007185-0","dataDeposito":"15/04/2021","titulares":[{"nomeCompleto":"FUNDAÇÃO UNIVERSIDADE DE BRASILIA","uf":"DF","pais":"BR"}],"despachos":[{"codigo":"2.10","titulo":"Requerimento de Pedido de Patente ou Certificado de Adição de Invenção","rpi":"2625"},{"codigo":"2.1","titulo":"Pedido de Patente ou Certificado de Adição de Invenção depositado","rpi":"2635"},{"codigo":"3.1","titulo":"Publicação do Pedido de Patente ou de Certificado de Adição de Invenção","rpi":"2702"}],"titulo":"CONTROLADOR ESOFÁGICO DE TEMPERATURA E RESFRIAMENTO  (CETER) E SEU USO DURANTE O PROCEDIMENTO DE ABLAÇÃO  CARDÍACA COM RADIOFREQUÊNCIA","IPC":["A61B 5/01","A61F 7/00"],"inventores":["SYLVIA DE SOUSA FARIA","PRISCILLA COSTA DE SOUZA","GABRIELA PESSOA SOUZA","ADSON FERREIRA DA ROCHA","SUELIA DE SIQUEIRA RODRIGUES FLEURY ROSA"]}