{"numero":"BR 12 2024 024360-1","dataDeposito":"01/06/2018","titulares":[{"nomeCompleto":"GENZYME CORPORATION","pais":"US"}],"divisaoPedido":{"dataDeposito":"01/06/2018","numero":"BR 11 2019 025095-6"},"despachos":[{"codigo":"2.10","titulo":"Notificação de recebimento do pedido de patente ou certificado de adição","rpi":"2813"},{"codigo":"2.4","titulo":"Pedido Dividido Depositado","rpi":"2820"},{"codigo":"3.1","titulo":"Pedido de Patente ou de Certificado de Adição de Invenção Publicado","rpi":"2822"}],"titulo":"MÉTODOS PARA PRODUZIR E PURIFICAR POLIPEPTÍDEOS TERAPÊUTICOS","IPC":["G01N 33/68"],"inventores":["MARTHA STAPELS","MICHELLE BUSCH"],"prioridadesUnionistas":[{"siglaPais":"US","numeroPrioridade":"62/514,587","dataPrioridade":"02/06/2017"}]}