{"numero":"BR 11 2014 022884-1","dataDeposito":"03/04/2013","IPC":["D04H 1/587","A47L 13/16","A61K 8/02","D04H 1/64","D06M 13/368","D06M 15/263","D21H 17/37","D21H 17/43","C08F 20/06","C08F 220/12"],"titulares":[{"nomeCompleto":"ROHM AND HAAS COMPANY","pais":"US"}],"despachos":[{"codigo":"6.21","titulo":"Exigência preliminar - pedidos com buscas realizadas por outros Escritórios de Patentes","rpi":"2539"},{"codigo":"9.1","titulo":"Deferimento","rpi":"2629"},{"codigo":"16.1","titulo":"Concessão de Patente ou Certificado de Adição de Invenção","rpi":"2640"}],"titulo":"MÉTODOS PARA FORMAR UM SUBSTRATO NÃO TECIDO DISPERSÍVEL EM UM MEIO AQUOSO, PARA FORNECER O MESMO, PARA FORNECER UM NÃO TECIDO DISPERSO EM UM MEIO AQUOSO, E, NÃO TECIDO DISPERSÍVEL EM UM MEIO AQUOSO","inventores":["Paul Nedwick","Maureen B. Nunn","Katherine Sue Rice"],"prioridadesUnionistas":[{"siglaPais":"US","numeroPrioridade":"61/622725","dataPrioridade":"11/04/2012"}]}