{"numero":"BR 11 2022 021040-0","pedidoInternacional":{"numeroPCT":"PCT IB2021/053116","dataPCT":"15/04/2021"},"publicacaoInternacional":{"numeroOMPI":"WO 2021/209945","dataOMPI":"21/10/2021"},"IPC":["A61K 9/00","A61K 9/16","A61K 9/20","A61K 31/58","A61P 35/00"],"prioridadesUnionistas":[{"siglaPais":"US","numeroPrioridade":"63/011,023","dataPrioridade":"16/04/2020"}],"despachos":[{"codigo":"1.1","titulo":"Publicação Internacional – PCT. Apresentação de petição de requerimento de entrada na fase nacional","rpi":"2703"},{"codigo":"1.3","titulo":"Notificação - Fase Nacional - PCT","rpi":"2709"}],"dataDeposito":"15/04/2021","dataFaseNacional":"17/10/2022","titulo":"MÉTODOS E COMPOSIÇÕES PARA O TRATAMENTO DE CÂNCER DE PRÓSTATA","titulares":[{"nomeCompleto":"TAVANTA THERAPEUTICS HUNGARY INCORPORATED","pais":"HU"}],"inventores":["RICHARD BALÁZS KÁRPÁTI","ZSOLT ÖTVÖS","TAMÁS JORDÁN","ANDREA UJHELYI","ORSOLYA BASA-DÉNES","TAMÁS SOLYMOSI","HRISTOS GLAVINAS","DOMINIC P. CAPONE","ELIZABETH MANNING DUUS","JOHN E. FRIEND II"]}