{"numero":"BR 11 2024 016966-9","pedidoInternacional":{"numeroPCT":"PCT CN2023/080757","dataPCT":"10/03/2023"},"publicacaoInternacional":{"numeroOMPI":"WO 2023/185416","dataOMPI":"05/10/2023"},"IPC":["B07C 5/34","B07C 5/36"],"prioridadesUnionistas":[{"siglaPais":"CN","numeroPrioridade":"202210315627.0","dataPrioridade":"28/03/2022"}],"despachos":[{"codigo":"1.1","titulo":"Pedido Internacional PCT Publicado. Petição de Requerimento de Entrada na Fase Nacional Recebida","rpi":"2799"},{"codigo":"1.3","titulo":"Pedido PCT Admitido na Fase Nacional","rpi":"2813"}],"dataDeposito":"10/03/2023","dataFaseNacional":"19/08/2024","titulo":"APARELHO DE SEPARAÇÃO DE MINERAIS A SECO","titulares":[{"nomeCompleto":"NUCTECH COMPANY LIMITED","pais":"CN"}],"inventores":["YUANJING LI","SHANGMIN SUN","CHUNGUANG ZONG","BICHENG LIU","WEIZHEN WANG","LEI LIU","QINGXIU JIN","CHENGJUN TAN"]}