{"numero":"BR 11 2016 027806-2","dataDeposito":"29/05/2015","IPC":["C22C 38/00","C21D 8/00","C21D 9/04","C22C 38/54"],"titulares":[{"nomeCompleto":"NIPPON STEEL CORPORATION","pais":"JP"}],"despachos":[{"codigo":"6.21","titulo":"Exigência preliminar - pedidos com buscas realizadas por outros Escritórios de Patentes","rpi":"2537"},{"codigo":"25.4","titulo":"Alteração de Nome Deferida","rpi":"2539"},{"codigo":"9.1","titulo":"Deferimento","rpi":"2612"},{"codigo":"11.4","titulo":"Arquivamento - Art. 38 § 2° da LPI","rpi":"2627"}],"titulo":"TRILHO E MÉTODO DE PRODUÇÃO PARA O MESMO"}