{"numero":"BR 11 2021 015704-2","pedidoInternacional":{"numeroPCT":"PCT EP2020/056651","dataPCT":"12/03/2020"},"publicacaoInternacional":{"numeroOMPI":"WO 2020/187686","dataOMPI":"24/09/2020"},"IPC":["A61Q 15/00","A61K 8/19","A61K 8/24","A61K 8/27","A61K 8/28","A61K 8/365"],"prioridadesUnionistas":[{"siglaPais":"CN","numeroPrioridade":"PCT/CN2019/078550","dataPrioridade":"18/03/2019"},{"siglaPais":"EP","numeroPrioridade":"19171731.3","dataPrioridade":"30/04/2019"}],"despachos":[{"codigo":"1.1","titulo":"Publicação Internacional – PCT. Apresentação de petição de requerimento de entrada na fase nacional","rpi":"2641"},{"codigo":"1.3","titulo":"Notificação - Fase Nacional - PCT","rpi":"2651"},{"codigo":"6.23","titulo":"Exigência preliminar - pedidos com buscas realizadas por outros Escritórios de Patentes - Art. 36 da LPI","rpi":"2821"}],"dataDeposito":"12/03/2020","dataFaseNacional":"10/08/2021","titulo":"COMPOSIÇÃO ANTIPERSPIRANTE AQUOSA, MÉTODO PARA REDUZIR A PERSPIRAÇÃO E USO DA COMPOSIÇÃO","titulares":[{"nomeCompleto":"UNILEVER IP HOLDINGS B.V.","pais":"PB"}],"inventores":["RENJIANG LIU","XIAOKE LI","WEINING LIU","HUANJUN ZHOU"]}