{"numero":"BR 10 2018 074259-0","dataDeposito":"26/11/2018","titulares":[{"nomeCompleto":"FELIPE FONSECA BASTOS","uf":"CE","pais":"BR"}],"despachos":[{"codigo":"2.10","titulo":"Requerimento de Pedido de Patente ou Certificado de Adição de Invenção","rpi":"2500"},{"codigo":"2.5","titulo":"Exigência - Art. 21 da LPI","rpi":"2502"},{"codigo":"15.7","titulo":"Petição não Conhecida","rpi":"2506"},{"codigo":"2.5","titulo":"Exigência - Art. 21 da LPI","rpi":"2507"},{"codigo":"2.1","titulo":"Pedido de Patente ou Certificado de Adição de Invenção depositado","rpi":"2513"},{"codigo":"3.1","titulo":"Publicação do Pedido de Patente ou de Certificado de Adição de Invenção","rpi":"2579"},{"codigo":"8.6","titulo":"Arquivamento - Art. 86 da LPI","rpi":"2650"},{"codigo":"8.11","titulo":"Manutenção do Arquivamento","rpi":"2666"}],"titulo":"BLOCO DE ENCHIMENTO SUSTENTÁVEL PARA ESTRUTURAS PRÉ MOLDADAS","IPC":["E04C 1/40","B29K 23/00","B29K 27/06"],"inventores":["Sigilo de Autor, conforme solicitado e com base no artigo 6º, § 4º da LPI"]}