{"numero":"BR 12 2018 071962-1","dataDeposito":"30/09/2013","titulares":[{"nomeCompleto":"PIRELLI TYRE S.P.A.","pais":"IT"}],"divisaoPedido":{"dataDeposito":"30/09/2013","numero":"BR 11 2015 007389-1"},"despachos":[{"codigo":"2.10","titulo":"Requerimento de Pedido de Patente ou Certificado de Adição de Invenção","rpi":"2496"},{"codigo":"2.4","titulo":"Notificação de Depósito do Pedido Dividido - Art 26 inciso I da LPI","rpi":"2501"},{"codigo":"9.1","titulo":"Deferimento","rpi":"2585"},{"codigo":"16.1","titulo":"Concessão de Patente ou Certificado de Adição de Invenção","rpi":"2599"}],"titulo":"MÉTODO PARA CONTROLAR A ESPESSURA DE UM ELEMENTO ALONGADO CONTÍNUO FEITO DE MATERIAL ELASTOMÉRICO","IPC":["B29D 30/16","B29D 30/30","B29C 47/00","B29C 47/34"],"inventores":["MARCO FABBRETTI","CESARE EMANUELE AMURRI","ANDREA CREPALDI","MAURIZIO MARCHINI"],"prioridadesUnionistas":[{"siglaPais":"IT","numeroPrioridade":"MI2012A001695","dataPrioridade":"09/10/2012"},{"siglaPais":"US","numeroPrioridade":"61/715,556","dataPrioridade":"18/10/2012"}]}