{"numero":"BR 11 2023 021876-4","pedidoInternacional":{"numeroPCT":"PCT CN2021/112897","dataPCT":"17/08/2021"},"publicacaoInternacional":{"numeroOMPI":"WO 2023/019414","dataOMPI":"23/02/2023"},"IPC":["H04W 72/12"],"despachos":[{"codigo":"1.1","titulo":"Pedido Internacional PCT Publicado. Petição de Requerimento de Entrada na Fase Nacional Recebida","rpi":"2756"},{"codigo":"1.3","titulo":"Pedido PCT Admitido na Fase Nacional","rpi":"2773"}],"dataDeposito":"17/08/2021","dataFaseNacional":"20/10/2023","titulo":"MÉTODO E DISPOSITIVO DE COMUNICAÇÃO SEM FIO","titulares":[{"nomeCompleto":"ZTE CORPORATION","pais":"CN"}],"inventores":["BO GAO","ZHAOHUA LU","KE YAO","SHUJUAN ZHANG","CHUANGXIN JIANG"]}