{"numero":"BR 10 2022 003671-3","dataDeposito":"25/02/2022","titulares":[{"nomeCompleto":"AIR PRODUCTS AND CHEMICALS, INC","pais":"US"}],"despachos":[{"codigo":"2.10","titulo":"Requerimento de Pedido de Patente ou Certificado de Adição de Invenção","rpi":"2670"},{"codigo":"2.1","titulo":"Pedido de Patente ou Certificado de Adição de Invenção depositado","rpi":"2673"},{"codigo":"3.1","titulo":"Publicação do Pedido de Patente ou de Certificado de Adição de Invenção","rpi":"2729"}],"titulo":"MÉTODO E APARELHO PARA GERENCIAR RECURSOS DE ENERGIA PREVISTOS PARA UM COMPLEXO DE INSTALAÇÕES DE GÁS INDUSTRIAL","IPC":["G05B 13/02","H02J 3/00"],"inventores":["SANJAY MEHTA","PRATIK MISRA"],"prioridadesUnionistas":[{"siglaPais":"US","numeroPrioridade":"17/193,029","dataPrioridade":"05/03/2021"}]}