{"numero":"BR 10 2016 030300-1","dataDeposito":"22/12/2016","titulo":"SISTEMAS POLIMÉRICOS CONSTITUÍDOS POR HIDROGEL, FILME AUTOSSUSTENTÁVEL E SISTEMA MICROPARTICULADO À BASE DE CITRULLUS LANATUS CONTENDO VITAMINAS DO COMPLEXO B, AMINOÁCIDOS ARGININA E CITRULINA E ZINCO PARA USO NA CICATRIZAÇÃO DE FERIMENTOS","IPC":["A61L 26/00","A61K 31/4415","A61K 31/714","A61K 31/519","A61K 31/155","A61K 36/42"],"titulares":[{"nomeCompleto":"UNIVERSIDADE FEDERAL DE PERNAMBUCO","uf":"PE","pais":"BR"}],"inventores":["ÉRICO MUNIZ DE ARRUDA FALCÃO","ALBERTO GALDINO DA SILVA JR.","MARIA DANIELLY LIMA DE OLIVEIRA","CÉSAR AUGUSTO SOUZA DE ANDRADE"],"despachos":[{"codigo":"3.1","titulo":"Publicação do Pedido de Patente ou de Certificado de Adição de Invenção","rpi":"2480"},{"codigo":"6.22","titulo":"Exigência preliminar - pedidos sem buscas realizadas por outros Escritórios de Patentes","rpi":"2554"},{"codigo":"7.1","titulo":"Conhecimento de Parecer Técnico","rpi":"2610"},{"codigo":"8.6","titulo":"Arquivamento - Art. 86 da LPI","rpi":"2611"},{"codigo":"8.7","titulo":"Restauração","rpi":"2623"},{"codigo":"9.2","titulo":"Indeferimento","rpi":"2636"},{"codigo":"12.2","titulo":"Recurso Contra o Indeferimento","rpi":"2646"},{"codigo":"8.6","titulo":"Arquivamento - Art. 86 da LPI","rpi":"2650"},{"codigo":"8.7","titulo":"Restauração","rpi":"2662"},{"codigo":"8.6","titulo":"Arquivamento - Art. 86 da LPI","rpi":"2703"},{"codigo":"8.7","titulo":"Restauração","rpi":"2721"},{"codigo":"8.6","titulo":"Arquivamento - Art. 86 da LPI","rpi":"2754"},{"codigo":"8.7","titulo":"Restauração","rpi":"2773"}]}