{"numero":"BR 12 2022 013114-0","dataDeposito":"07/12/2017","titulares":[{"nomeCompleto":"ADAMA MAKHTESHIM LTD.","pais":"IL"}],"divisaoPedido":{"dataDeposito":"07/12/2017","numero":"BR 11 2019 011777-6"},"despachos":[{"codigo":"2.10","titulo":"Requerimento de Pedido de Patente ou Certificado de Adição de Invenção","rpi":"2688"},{"codigo":"2.4","titulo":"Notificação de Depósito do Pedido Dividido - Art 26 inciso I da LPI","rpi":"2694"},{"codigo":"7.1","titulo":"Conhecimento de Parecer Técnico","rpi":"2709"},{"codigo":"9.2","titulo":"Indeferimento","rpi":"2742"},{"codigo":"12.2","titulo":"Recurso Contra o Indeferimento","rpi":"2752"}],"titulo":"FORMULAÇÕES SÓLIDAS E MÉTODOS DE PREPARAÇÃO DAS MESMAS,  FORMULAÇÃO DE FERTILIZANTE, COMPOSIÇÃO, MÉTODO PARA CONTROLAR OU PREVENIR UMA DOENÇA,  MÉTODO PARA CONTROLAR VEGETAÇÃO E INSETOS INDESEJADOS E  EMBALAGEM"}