{"numero":"BR 11 2015 012746-0","dataDeposito":"05/12/2013","titulares":[{"nomeCompleto":"CHIESI FARMACEUTICI S.P.A.","pais":"IT"}],"despachos":[{"codigo":"7.5","titulo":"Notificação de Anuência relacionada com o Art. 229-C da LPI","rpi":"2524"},{"codigo":"6.21","titulo":"Exigência preliminar - pedidos com buscas realizadas por outros Escritórios de Patentes","rpi":"2538"},{"codigo":"6.1","titulo":"Exigência Técnica","rpi":"2613"},{"codigo":"9.1","titulo":"Deferimento","rpi":"2639"},{"codigo":"11.4","titulo":"Arquivamento - Art. 38 § 2° da LPI","rpi":"2654"}],"IPC":["C07D 453/02","A61K 31/439","A61P 11/06","A61P 31/08"],"titulo":"COMPOSTO, COMPOSIÇÃO FARMACÊUTICA, DISPOSITIVO, USO DE UM COMPOSTO E COMBINAÇÃO DE UM COMPOSTO"}