{"numero":"BR 11 2024 012643-9","pedidoInternacional":{"numeroPCT":"PCT GB2022/053230","dataPCT":"14/12/2022"},"publicacaoInternacional":{"numeroOMPI":"WO 2023/118812","dataOMPI":"29/06/2023"},"IPC":["H01M 4/131"],"prioridadesUnionistas":[{"siglaPais":"GB","numeroPrioridade":"2118598.8","dataPrioridade":"21/12/2021"},{"siglaPais":"GB","numeroPrioridade":"2201717.2","dataPrioridade":"10/02/2022"}],"despachos":[{"codigo":"1.1","titulo":"Pedido Internacional PCT Publicado. Petição de Requerimento de Entrada na Fase Nacional Recebida","rpi":"2791"},{"codigo":"1.3","titulo":"Pedido PCT Admitido na Fase Nacional","rpi":"2802"},{"codigo":"28.10.32","titulo":"Notificação de requerimento de trâmite prioritário de PPH","rpi":"2823"},{"codigo":"28.30","titulo":"Trâmite prioritário admitido","rpi":"2824"}],"dataDeposito":"14/12/2022","dataFaseNacional":"20/06/2024","titulo":"ELETRODO, BATERIA DE ÍONS DE METAL, DISPOSITIVO ELETROQUÍMICO, E, MÉTODO PARA FABRICAÇÃO DE UM ELETRODO","titulares":[{"nomeCompleto":"ECHION TECHNOLOGIES LIMITED","pais":"GB"}],"inventores":["PETER SLATER","DANIEL MARTIN","ALEXANDER GROOMBRIDGE"]}