{"numero":"BR 11 2023 012018-7","pedidoInternacional":{"numeroPCT":"PCT US2021/064073","dataPCT":"17/12/2021"},"publicacaoInternacional":{"numeroOMPI":"WO 2022/133239","dataOMPI":"23/06/2022"},"IPC":["C07K 16/42","A61P 9/12","A61K 31/165"],"prioridadesUnionistas":[{"siglaPais":"US","numeroPrioridade":"63/127,959","dataPrioridade":"18/12/2020"}],"despachos":[{"codigo":"1.1","titulo":"Publicação Internacional – PCT. Apresentação de petição de requerimento de entrada na fase nacional","rpi":"2738"},{"codigo":"1.3","titulo":"Notificação - Fase Nacional - PCT","rpi":"2746"}],"dataDeposito":"17/12/2021","dataFaseNacional":"16/06/2023","titulo":"PROTEÍNAS DE IMUNOGLOBULINA QUE SE LIGAM A AGONISTAS DE NPR1","titulares":[{"nomeCompleto":"REGENERON PHARMACEUTICALS, INC.","pais":"US"}],"inventores":["MICHAEL DUNN","LORI MORTON","NEIL STAHL","TAMMY HUANG","ISHITA CHATTERJEE","VISHAL KAMAT","ASHIQUE RAFIQUE"]}