{"numero":"BR 11 2014 031011-4","dataDeposito":"13/06/2013","titulares":[{"nomeCompleto":"WEST DRILLING PRODUCTS AS","pais":"NO"}],"despachos":[{"codigo":"6.6.1","titulo":"Exigência Formal - art. 38 (I) da Lei 13.123/2015","rpi":"2500"},{"codigo":"6.21","titulo":"Exigência preliminar - pedidos com buscas realizadas por outros Escritórios de Patentes","rpi":"2561"},{"codigo":"9.1","titulo":"Deferimento","rpi":"2590"},{"codigo":"16.1","titulo":"Concessão de Patente ou Certificado de Adição de Invenção","rpi":"2601"}],"IPC":["E21B 19/16","E21B 21/10"],"titulo":"ARRANJO PARA A CIRCULAÇÃO CONTÍNUA DE FLUIDO DE PERFURAÇÃO DURANTE AS OPERAÇÕES DE PERFURAÇÃO","inventores":["ODD B. SKJAERSETH","BJØRN EILERTSEN"],"prioridadesUnionistas":[{"siglaPais":"NO","numeroPrioridade":"20120701","dataPrioridade":"18/06/2012"}]}