{"numero":"BR 11 2015 007320-4","dataDeposito":"07/10/2013","titulares":[{"nomeCompleto":"ASK S.A.","pais":"FR"}],"despachos":[{"codigo":"6.6.1","titulo":"Exigência Formal - art. 38 (I) da Lei 13.123/2015","rpi":"2498"},{"codigo":"6.21","titulo":"Exigência preliminar - pedidos com buscas realizadas por outros Escritórios de Patentes","rpi":"2560"},{"codigo":"9.1","titulo":"Deferimento","rpi":"2655"},{"codigo":"16.1","titulo":"Concessão de Patente ou Certificado de Adição de Invenção","rpi":"2667"}],"IPC":["G06K 19/077"],"titulo":"CARTÃO INTELIGENTE SEM CONTATO EM MULTICAMADAS, E, PROCESSO PARA  A FABRICAÇÃO DE UM CARTÃO INTELIGENTE SEM CONTATO","inventores":["PIERRE BENATO"],"prioridadesUnionistas":[{"siglaPais":"FR","numeroPrioridade":"1202671","dataPrioridade":"05/10/2012"}]}