{"numero":"BR 10 2014 012450-0","dataDeposito":"13/05/2014","titulo":"MÉTODO DE FABRICAÇÃO ASSÉPTICA DE IMPLANTE INJETÁVEL À BASE DO POLÍMERO ACRÍLICO POLIMETLMETACRILATO, ACRESCIDO DE CARBOXIMETILCELULOSE DE SÓDIO, ÁCIDO ETILENODIAMINOTETACÉTICO E RINGER SEM LACTADO NA FORMA DE GEL VISCOSO ESTÉRIL","IPC":["A61L 27/14","A61L 27/20","A61L 27/52","A61K 8/04"],"titulares":[{"nomeCompleto":"DANILO VIEIRA DE ALCANTARA","uf":"RJ","pais":"BR"},{"nomeCompleto":"SAMUEL DA SILVA MAURÍCIO","uf":"RJ","pais":"BR"}],"inventores":["ARTIGO 6 - PARAGRAFO 4º DA LEI 9.279/96"],"despachos":[{"codigo":"3.1","titulo":"Publicação do Pedido de Patente ou de Certificado de Adição de Invenção","rpi":"2475"},{"codigo":"3.7","titulo":"Publicação Anulada","rpi":"2477"}]}