{"numero":"BR 11 2019 008074-0","pedidoInternacional":{"numeroPCT":"PCT EP2017/076802","dataPCT":"19/10/2017"},"publicacaoInternacional":{"numeroOMPI":"WO 2018/073395","dataOMPI":"26/04/2018"},"IPC":["G01R 31/28","G01R 31/319"],"prioridadesUnionistas":[{"siglaPais":"US","numeroPrioridade":"62/410,666","dataPrioridade":"20/10/2016"}],"despachos":[{"codigo":"1.1","titulo":"Publicação Internacional – PCT. Apresentação de petição de requerimento de entrada na fase nacional","rpi":"2521"},{"codigo":"1.3","titulo":"Notificação - Fase Nacional - PCT","rpi":"2530"},{"codigo":"15.35","titulo":"Atualização de informações no portal","rpi":"2648"},{"codigo":"6.23","titulo":"Exigência preliminar - pedidos com buscas realizadas por outros Escritórios de Patentes","rpi":"2690"},{"codigo":"9.1","titulo":"Deferimento","rpi":"2736"},{"codigo":"16.1","titulo":"Concessão de Patente ou Certificado de Adição de Invenção","rpi":"2745"}],"dataDeposito":"19/10/2017","dataFaseNacional":"18/04/2019","titulo":"SISTEMA E MÉTODO PARA TESTAR UM RECURSO DE UM SISTEMA INTEGRADO","titulares":[{"nomeCompleto":"Y SOFT CORPORATION, A.S.","pais":"CZ"}],"inventores":["VÁCLAV NOVOTNÝ","JIRI KYZLINK","JAKUB PAVLÁK","ALES PERNIKÁR","ONDREJ KRAJICEK"]}