{"numero":"BR 11 2017 015312-2","dataDeposito":"14/01/2016","dataFaseNacional":"17/07/2017","pedidoInternacional":{"numeroPCT":"PCT JP2016/050975","dataPCT":"14/01/2016"},"publicacaoInternacional":{"numeroOMPI":"WO 2016/117444","dataOMPI":"28/07/2016"},"titulo":"MOTOR DE COMBUSTÍVEL FLEXÍVEL","IPC":["F02D 13/02","F02D 19/08"],"titulares":[{"nomeCompleto":"MAZDA MOTOR CORPORATION","pais":"JP"}],"inventores":["TOMOMI WATANABE","NOBUYUKI FURUICHI","SHO SHIMAMOTO","MIKINORI OHASHI","SHIGEYUKI HIRASHITA"],"prioridadesUnionistas":[{"siglaPais":"JP","numeroPrioridade":"2015-007503","dataPrioridade":"19/01/2015"}],"despachos":[{"codigo":"1.3","titulo":"Notificação - Fase Nacional - PCT","rpi":"2479"},{"codigo":"6.6.1","titulo":"Exigência Formal - art. 38 (I) da Lei 13.123/2015","rpi":"2495"},{"codigo":"6.21","titulo":"Exigência preliminar - pedidos com buscas realizadas por outros Escritórios de Patentes","rpi":"2584"},{"codigo":"11.2","titulo":"Arquivamento - Art. 36 §1° da LPI","rpi":"2599"}]}