{"numero":"BR 11 2025 000243-0","pedidoInternacional":{"numeroPCT":"PCT US2023/069389","dataPCT":"29/06/2023"},"publicacaoInternacional":{"numeroOMPI":"WO 2024/026189","dataOMPI":"01/02/2024"},"IPC":["H04B 7/06","H04B 7/08","H04W 16/28","H04L 1/00"],"prioridadesUnionistas":[{"siglaPais":"US","numeroPrioridade":"17/814,686","dataPrioridade":"25/07/2022"}],"despachos":[{"codigo":"1.1","titulo":"Pedido Internacional PCT Publicado. Petição de Requerimento de Entrada na Fase Nacional Recebida","rpi":"2822"}]}