{"numero":"BR 20 2018 002700-5","dataDeposito":"08/02/2018","titulo":"DISPOSIÇÃO CONSTRUTIVA EM DISPOSITIVO PARA EXTRAÇÃO DE LEITE MATERNO","IPC":["A61M 1/06"],"titulares":[{"nomeCompleto":"SERGIO PORTO","uf":"RJ","pais":"BR"}],"inventores":["SERGIO PORTO"],"despachos":[{"codigo":"3.2","titulo":"Publicação Antecipada","rpi":"2477"},{"codigo":"28.10.1","titulo":"Notificação de requerimento de trâmite prioritário de depositante idoso","rpi":"2534"},{"codigo":"28.30","titulo":"Trâmite prioritário concedido","rpi":"2535"},{"codigo":"7.1","titulo":"Conhecimento de Parecer Técnico","rpi":"2537"},{"codigo":"9.1","titulo":"Deferimento","rpi":"2553"},{"codigo":"16.1","titulo":"Concessão de Patente ou Certificado de Adição de Invenção","rpi":"2557"}]}