{"numero":"MU 9100007-6","dataDeposito":"10/02/2011","titulo":"BRAQUETE ORTODÔNTICO GEMINADO COM CANALETA E TUBO HORIZONTAL PARA COLAGEM OU SOLDAGEM","titulares":[{"nomeCompleto":"Dauro Douglas Oliveira","uf":"MG","pais":"BR"},{"nomeCompleto":"José Eymard Bicalho","uf":"MG","pais":"BR"},{"nomeCompleto":"Jánes Landre Júnior","uf":"MG","pais":"BR"},{"nomeCompleto":"MARIA LÚCIA ALMEIDA HAUEISEN DE SOUZA","uf":"MG","pais":"BR"}],"despachos":[{"codigo":"9.2","titulo":"Indeferimento","rpi":"2479"},{"codigo":"3.8","titulo":"Retificação","rpi":"2485"},{"codigo":"9.2.4","titulo":"Manutenção do Indeferimento","rpi":"2493"}],"IPC":["A61C 7/16"],"inventores":["MARIA LÚCIA ALMEIDA HAUEISEN DE SOUZA","Dauro Douglas Oliveira","José Eymard Bicalho","JÁNES LANDRE JÚNIOR"]}