{"numero":"MU 9102465-0","dataDeposito":"30/09/2011","titulo":"LACRE ENCAIXÁVEL MULTIUSO","IPC":["B65D 55/00"],"titulares":[{"nomeCompleto":"ZILBER CARDOZO DO NASCIMENTO","uf":"RJ","pais":"BR"}],"inventores":["ZILBER CARDOZO DO NASCIMENTO"],"despachos":[{"codigo":"3.1","titulo":"Publicação do Pedido de Patente ou de Certificado de Adição de Invenção","rpi":"2521"},{"codigo":"8.6","titulo":"Arquivamento - Art. 86 da LPI","rpi":"2522"},{"codigo":"8.11","titulo":"Manutenção do Arquivamento","rpi":"2538"}]}