{"numero":"PI 0410261-4","dataDeposito":"12/05/2004","titulares":[{"nomeCompleto":"F.Hoffmann-La Roche AG","pais":"CH"}],"despachos":[{"codigo":"121","titulo":"Exigência","rpi":"2526"},{"codigo":"121","titulo":"Exigência","rpi":"2544"},{"codigo":"100","titulo":"Recurso conhecido e provido. Reformada a Decisão recorrida e deferido o pedido","rpi":"2558"},{"codigo":"16.1","titulo":"Concessão de Patente ou Certificado de Adição de Invenção","rpi":"2566"},{"codigo":"16.3","titulo":"Retificação","rpi":"2638"}],"titulo":"ANTICORPO MONOCLONAL QUE SE LIGA ESPECIFICAMENTE AO proBNP, MÉTODOS PARA DETECÇÃO ESPECÍFICA DE proBNP IN VITRO E PARA DIAGNÓSTICO DE INSUFICIÊNCIA CARDÍACA IN VITRO, KIT PARA MEDIÇÃO DE proBNP, E LINHAGEM CELULAR DE HIBRIDOMA MAB 1.21.3","IPC":["C07K 16/26","G01N 33/531","G01N 33/68","G01N 33/74","C12N 5/20"],"inventores":["Volker Klemt","Anneliese Borgya","Andreas Gallusser","Michael Grol","Klaus Hallermayer","Christoph Seidel"],"prioridadesUnionistas":[{"siglaPais":"EP","numeroPrioridade":"03 010591.0","dataPrioridade":"12/05/2003"}],"dataConcessao":"10/03/2020"}