{"numero":"PI 0721745-5","dataDeposito":"13/07/2007","pedidoInternacional":{"numeroPCT":"PCT ES2007/000425","dataPCT":"13/07/2007"},"publicacaoInternacional":{"numeroOMPI":"WO 2009/010594","dataOMPI":"22/01/2009"},"titulares":[{"nomeCompleto":"FAST DRINKS 2005 S.L.","pais":"ES"}],"despachos":[{"codigo":"1.5","titulo":"Exigências Diversas","rpi":"2475"},{"codigo":"1.3","titulo":"Notificação - Fase Nacional - PCT","rpi":"2488"},{"codigo":"6.20","titulo":"ExigênciaPré-Exame – Art. 34 da LPI","rpi":"2489"},{"codigo":"11.5","titulo":"Arquivamento - Art. 34 da LPI","rpi":"2505"},{"codigo":"11.20","titulo":"Manutenção do arquivamento","rpi":"2594"}],"dataFaseNacional":"12/01/2010","titulo":"RECIPIENTE AUTOAQUECÍVEL","IPC":["B65D 81/34"],"inventores":["SANTIAGO CANELA MERCADE"]}