{"numero":"PI 0416213-7","dataDeposito":"19/11/2004","dataConcessao":"14/02/2017","titulares":[{"nomeCompleto":"MICROPORT ORTHOPEDICS HOLDINGS INC.","pais":"US"}],"despachos":[{"codigo":"25.1","titulo":"Transferência Deferida","rpi":"2475"},{"codigo":"16.3","titulo":"Retificação","rpi":"2633"},{"codigo":"21.6","titulo":"Extinção da patente para fins da restauração nos termos do art. 87 da LPI.","rpi":"2645"},{"codigo":"24.10","titulo":"Manutenção da Extinção - Art. 78 inciso IV da LPI","rpi":"2661"}],"titulo":"PRESILHA GUIA PARA A ORIENTAÇÃO DA COLOCAÇÃO DE FIO-GUIA NO FÊMUR","IPC":["A61B 17/17"],"inventores":["Michael B. Sheldon","Ramon Luna","Steven F. Seyer","Brian Krehlik"],"prioridadesUnionistas":[{"siglaPais":"US","numeroPrioridade":"60/523,799","dataPrioridade":"20/11/2003"}]}