{"numero":"PI 0925013-1","dataDeposito":"17/04/2009","titulares":[{"nomeCompleto":"Alcatel Lucent","pais":"FR"}],"despachos":[{"codigo":"6.6.1","titulo":"Exigência Formal - art. 38 (I) da Lei 13.123/2015","rpi":"2507"},{"codigo":"6.21","titulo":"Exigência preliminar - pedidos com buscas realizadas por outros Escritórios de Patentes","rpi":"2550"},{"codigo":"15.11","titulo":"Alteração de Classificação","rpi":"2555"},{"codigo":"9.1","titulo":"Deferimento","rpi":"2598"},{"codigo":"16.1","titulo":"Concessão de Patente ou Certificado de Adição de Invenção","rpi":"2610"},{"codigo":"21.6","titulo":"Extinção - Art. 86 da LPI","rpi":"2771"},{"codigo":"24.10","titulo":"Manutenção da Extinção - Art. 78 inciso IV da LPI","rpi":"2787"}],"IPC":["H04B 7/26","H04L 5/00","H04W 72/04","H04W 84/04"],"titulo":"MÉTODO E APARELHO DE PROCESSAMENTO PARA SELEÇÃO DE USUÁRIO DE RETRANSMISSÃO E ALOCAÇÃO DE RECURSO DE ENLACE DESCENDENTE EM UMA ESTAÇÃO BASE DE UM SISTEMA DE COMUNICAÇÃO DE RETRANSMISSÃO E ESTAÇÃO BASE PARA UM SISTEMA DE COMUNICAÇÃO DE RETRANSMISSÃO","inventores":["XIAOBO ZHANG","MINGLI YOU"],"dataConcessao":"12/01/2021"}