{"numero":"PI 0715360-0","dataDeposito":"21/07/2007","titulares":[{"nomeCompleto":"Wyeth","pais":"US"}],"despachos":[{"codigo":"6.20","titulo":"ExigênciaPré-Exame – Art. 34 da LPI","rpi":"2489"},{"codigo":"1.1.1","titulo":"Retificação","rpi":"2494"},{"codigo":"7.4","titulo":"Ciência relacionada com o Art. 229-C da LPI","rpi":"2494"},{"codigo":"7.5","titulo":"Notificação de Anuência relacionada com o Art. 229-C da LPI","rpi":"2552"},{"codigo":"7.1","titulo":"Conhecimento de Parecer Técnico","rpi":"2572"},{"codigo":"6.1","titulo":"Exigência Técnica","rpi":"2587"},{"codigo":"9.1","titulo":"Deferimento","rpi":"2604"},{"codigo":"16.1","titulo":"Concessão de Patente ou Certificado de Adição de Invenção","rpi":"2611"},{"codigo":"16.3","titulo":"Retificação","rpi":"2629"},{"codigo":"16.3","titulo":"Retificação","rpi":"2661"}],"pedidoInternacional":{"numeroPCT":"PCT US2007/016917","dataPCT":"21/07/2007"},"publicacaoInternacional":{"numeroOMPI":"WO 2008/013943","dataOMPI":"31/01/2008"},"IPC":["C12P 21/06","C12N 9/14","C12N 9/64"],"prioridadesUnionistas":[{"siglaPais":"US","numeroPrioridade":"833,479","dataPrioridade":"27/07/2006"}],"titulo":"MÉTODO PARA A PRODUÇÃO DE UMA PROTEÍNA RECOMBINANTE; MÉTODO PARA A PRODUÇÃO DE UMA PROTEÍNA 2086 MENINGOCÓCICA RECOMBINANTE (P2086); E COMPOSIÇÃO","inventores":["WEI-QIANG WILLIE SUN","EARL PURSELL"],"dataConcessao":"19/01/2021"}