{"numero":"PI 0702963-2","dataDeposito":"22/03/2007","titulo":"FIXADOR CIRÚRGICO E CORTADOR COM EXECUTOR DE EXTREMIDADE POR IMITAÇÃO","IPC":["A61B 17/32","A61B 17/03","A61B 17/00"],"titulares":[{"nomeCompleto":"Johnson & Johnson","pais":"US"}],"inventores":["Mark S. Ortiz","Frederick E. Shelton IV"],"prioridadesUnionistas":[{"siglaPais":"US","numeroPrioridade":"11/277,328","dataPrioridade":"23/03/2006"}],"despachos":[{"codigo":"16.1","titulo":"Concessão de Patente ou Certificado de Adição de Invenção","rpi":"2476"},{"codigo":"16.3","titulo":"Retificação","rpi":"2633"},{"codigo":"21.6","titulo":"Extinção - Art. 86 da LPI","rpi":"2767"},{"codigo":"24.10","titulo":"Manutenção da Extinção - Art. 78 inciso IV da LPI","rpi":"2783"}],"dataConcessao":"19/06/2018"}