{"numero":"PI 0618283-6","dataDeposito":"10/11/2006","titulares":[{"nomeCompleto":"Laboratoires Fournier S.A.","pais":"FR"}],"despachos":[{"codigo":"6.20","titulo":"ExigênciaPré-Exame – Art. 34 da LPI","rpi":"2488"},{"codigo":"7.4","titulo":"Ciência relacionada com o Art. 229-C da LPI","rpi":"2525"},{"codigo":"7.5","titulo":"Notificação de Anuência relacionada com o Art. 229-C da LPI","rpi":"2554"},{"codigo":"7.1","titulo":"Conhecimento de Parecer Técnico","rpi":"2556"},{"codigo":"9.2","titulo":"Indeferimento","rpi":"2575"},{"codigo":"12.2","titulo":"Recurso Contra o Indeferimento","rpi":"2587"},{"codigo":"120","titulo":"Tome Conhecimento do Parecer Técnico","rpi":"2718"},{"codigo":"111","titulo":"Recurso conhecido e negado provimento. Mantido o indeferimento do pedido","rpi":"2738"}],"titulo":"USO DE FENOFIBRATO OU DE UM DERIVADO DESTE PARA A PREVENÇÃO DA RETINOPATIA DIABÉTICA"}