{"numero":"PI 0411994-0","dataDeposito":"25/06/2004","titulares":[{"nomeCompleto":"Monsanto Technology LLC","pais":"US"}],"despachos":[{"codigo":"121","titulo":"Exigência","rpi":"2527"},{"codigo":"100","titulo":"Recurso conhecido e provido. Reformada a Decisão recorrida e deferido o pedido","rpi":"2550"},{"codigo":"16.1","titulo":"Concessão de Patente ou Certificado de Adição de Invenção","rpi":"2560"}],"titulo":"MOLÉCULA DE ÁCIDO NUCLÉICO CODIFICANDO PROTEÍNAS ÚTEIS PARA AUMENTAR OS NÍVEIS DE ÓLEO EM PLANTAS, CASSETE DE EXPRESSÃO E MÉTODO DE PRODUZIR UMA PLANTA TENDO NÍVEIS AUMENTADOS DE PRODUÇÃO DE ÓLEO","IPC":["C12N 5/10","C12N 15/29","C12N 15/82","C12P 7/64","C12P 19/04","A01H 5/00","A01H 5/10"],"inventores":["Monica P. Ravanello","Terry J. Foley","John R. Ledeaux","Annette E. Wyrick","Thomas J. Savage"],"prioridadesUnionistas":[{"siglaPais":"US","numeroPrioridade":"60/483.491","dataPrioridade":"27/06/2003"},{"siglaPais":"US","numeroPrioridade":"10/877.645","dataPrioridade":"25/06/2004"}]}