{"numero":"PI 1007846-0","dataDeposito":"22/02/2010","titulares":[{"nomeCompleto":"PARAT P2H AS","pais":"NO"}],"despachos":[{"codigo":"6.6.1","titulo":"Exigência Formal - art. 38 (I) da Lei 13.123/2015","rpi":"2506"},{"codigo":"6.21","titulo":"Exigência preliminar - pedidos com buscas realizadas por outros Escritórios de Patentes","rpi":"2545"},{"codigo":"9.1","titulo":"Deferimento","rpi":"2587"},{"codigo":"16.1","titulo":"Concessão de Patente ou Certificado de Adição de Invenção","rpi":"2596"},{"codigo":"25.1","titulo":"Transferência Deferida","rpi":"2728"}],"IPC":["F22B 1/30","F24H 1/20"],"titulo":"Caldeira de eletrodos para uso em ambiente marinho","inventores":["MARTIN LØVLAND"],"prioridadesUnionistas":[{"siglaPais":"NO","numeroPrioridade":"20090808","dataPrioridade":"20/02/2009"}],"dataConcessao":"06/10/2020"}